{
    "main_menu_user": [
        {"name": "Home", "url_name": "index", "class": "fa-home"},
        {"name": "Albums", "class": "fa-folder-open", "id": "1",
        "sub1": {"name": "All Albums", "url_name": "show_albums_list", "id": "11", "class": "fa-folder-open"},
        "sub2": {"name": "My Albums", "url_name": "user_albums_list/{user_id}" , "id": "12", "class": "fa-address-book-o"},
        "sub3": {"name": "Create Album", "url_name": "add_album", "id": "13", "class": "fa-plus"}
        },
        {"name": "Photos", "class": "fa-file-image-o", "id": "2",
        "sub1": {"name": "All Photos", "url_name": "show_photos_list", "id": "21", "class": "fa-file-image-o"},
        "sub2": {"name": "My Photos", "url_name": "user_photo_list/{user_id}", "id": "22", "class": "fa-camera"},
        "sub3": {"name": "Upload Photo", "url_name": "add_photo", "id": "23", "class": "fa-download"}
        },
        {"name": "Profile", "class": "fa-user", "id": "3",
        "sub1": {"name": "{username}", "url_name": "profile/{user_id}", "id": "31", "class": " fa-address-card-o"},
        "sub2": {"name": "Logout", "url_name": "logout", "id": "32", "class": "fa-sign-out"}
        }
    ],

    "main_menu_guest": [
        {"name": "Home", "url_name": "index", "class": "fa-home"},
        {"name": "Albums", "url_name": "show_albums_list", "class": "fa-folder-open", "id": "1"},
        {"name": "Photo", "url_name": "show_photos_list", "class": "fa-file-image-o", "id": "2"},
        {"name": "Login", "class": "fa-sign-in", "id": "3",
        "sub1": {"name": "Login", "url_name": "#", "id": "window", "class": "fa-sign-in"},
        "sub2": {"name": "Join us", "url_name": "registration", "id": "32", "class": "fa-sign-in"}
        }
    ]
}

